{
	"nameShort": "Code - OSS",
	"nameLong": "Code - OSS",
	"applicationName": "code-oss",
	"dataFolderName": ".vscode-oss",
	"win32MutexName": "vscodeoss",
	"licenseName": "MIT",
	"licenseUrl": "https://github.com/Microsoft/vscode/blob/master/LICENSE.txt",
	"win32DirName": "Microsoft Code OSS",
	"win32NameVersion": "Microsoft Code OSS",
	"win32RegValueName": "CodeOSS",
	"win32AppId": "{{E34003BB-9E10-4501-8C11-BE3FAA83F23F}",
	"win32x64AppId": "{{D77B7E06-80BA-4137-BCF4-654B95CCEBC5}",
	"win32AppUserModelId": "Microsoft.CodeOSS",
	"win32ShellNameShort": "C&ode - OSS",
	"darwinBundleIdentifier": "com.visualstudio.code.oss",
	"reportIssueUrl": "https://github.com/Microsoft/vscode/issues/new",
	"urlProtocol": "code-oss",
	"extensionAllowedProposedApi": [
		"ms-vscode.node-debug",
		"ms-vscode.node-debug2"
	],
	"commit": "cc11eb00ba83ee0b6d29851f1a599cf3d9469932",
	"date": "2018-03-14T13:43:23.071Z",
	"checksums": {
		"vs/workbench/workbench.main.js": "XPGTaIeEBTtuvZ5AsCNsuA",
		"vs/workbench/workbench.main.css": "3EWcPA8zCZJJL232wCFpMg",
		"vs/workbench/electron-browser/bootstrap/index.html": "/Tgz9oebstmTGvDlTpbgpg",
		"vs/workbench/electron-browser/bootstrap/index.js": "6GzYQ3n+vVosb3zkbomCNg",
		"vs/workbench/electron-browser/bootstrap/preload.js": "Pn3YhaXsTjBGy5Gqi+oVgw"
	},
	"settingsSearchBuildId": 122000659
}